{"sections":{"1651070082ce909d70":{"type":"rich-text","blocks":{"1651070082821edb4d-0":{"type":"text","settings":{"enlarge_text":true,"text":"<h2>GET IN TOUCH<\/h2>"}},"1651070082821edb4d-1":{"type":"text","settings":{"enlarge_text":false,"text":"<p>We’re always here to help. <br\/>Select your preferred contact method or contact reason to start.<\/p>"}}},"block_order":["1651070082821edb4d-0","1651070082821edb4d-1"],"custom_css":["h2 {font-weight: 600;}","@media (min-width: 769px) {h2 {font-size: 32px; }}","@media (max-width: 767px) {.custom-rich-text .page-width > div .enlarge-text {display: block; } .custom-rich-text > div > div {padding: 0px 10px; margin: 0px 0 30px; } h2 {font-size: 25px; } .custom-rich-text div p {font-size: 18px; }}"],"settings":{"desktop_hide":false,"mobile_hide":false,"align_text":"center","narrow_column":false,"divider":false,"padding_b":0}},"rich_text_qARr8A":{"type":"rich-text","blocks":{"text_ewEtt3":{"type":"text","settings":{"enlarge_text":false,"text":"<h3>General Inquiries<\/h3>"}},"text_R9NKJT":{"type":"text","settings":{"enlarge_text":false,"text":"<p>We are reachable Monday to Friday from 9:30am to 17:00pm (CET).<\/p>"}}},"block_order":["text_ewEtt3","text_R9NKJT"],"custom_css":[".theme-block,h3 {margin: 0; text-transform: none;}",".custom-rich-text {margin-bottom: 25px;}","h3 {font-family: \"Montserrat\" !important; text-transform: capitalize; font-weight: 600; margin-bottom: 10px; font-size: 20px;}","@media (min-width: 769px) {h3 {font-size: 25px; }}","@media (max-width: 767px) {.custom-rich-text div p {font-size: 18px; } .custom-rich-text > div > div {padding: 0px 10px; margin: 0; } .custom-rich-text {margin-bottom: 0; }}"],"settings":{"desktop_hide":false,"mobile_hide":false,"align_text":"center","narrow_column":false,"divider":false,"padding_b":0}},"16510701485bc85b9d":{"type":"text-columns","blocks":{"16510701486e16a223-0":{"type":"text_block","disabled":true,"settings":{"enable_image":false,"image_mask":"none","image_width":200,"title":"","text":"","style_link":false,"chat_btn":true,"button_label":"OPEN THE CHAT","button_link":"#live-chat"}},"16510701486e16a223-2":{"type":"text_block","settings":{"enable_image":false,"image":"shopify:\/\/shop_images\/Icon_2.jpg","image_mask":"none","image_width":200,"title":"","text":"","style_link":false,"chat_btn":false,"button_label":"EMAIL US AT CIAO@MARCODALMASO.COM","button_link":"mailto:ciao@marcodalmaso.com"}},"16510701486e16a223-1":{"type":"text_block","settings":{"enable_image":false,"image":"shopify:\/\/shop_images\/Icon_3.jpg","image_mask":"none","image_width":200,"title":"","text":"","style_link":false,"chat_btn":false,"button_label":"CALL US AT +39 0444 340888","button_link":"tel:+390444340888"}}},"block_order":["16510701486e16a223-0","16510701486e16a223-2","16510701486e16a223-1"],"custom_css":[".btn {min-width: 100%; background: #000; color: #fff;}",".grid__item {padding-left: 0; max-width: 362px;}",".grid {margin: 0; display: flex; justify-content: center; gap: 58px;}","@media (max-width: 767px) {.custom-collection-list:nth-child(odd) > div {padding: 0 30px; } .custom-collection-list div > div .grid__item {width: 100%; margin-bottom: 12px !important; } .grid {flex-direction: column; gap: 12px; }}"],"settings":{"title":"","btntext":"","btnurl":"","text":"","align_text":"center","divider":false,"mobile_link":""}},"165269900644ff2f31":{"type":"text-columns","blocks":{"1652699006e9e7c9bd-0":{"type":"text_block","settings":{"enable_image":false,"image":"shopify:\/\/shop_images\/Icon_6.jpg","image_mask":"none","image_width":200,"title":"Press Inquiries","text":"","style_link":false,"chat_btn":false,"button_label":"GO TO PRESS INQUIRY FORM","button_link":"shopify:\/\/pages\/press-inquiries"}},"1652699006e9e7c9bd-1":{"type":"text_block","settings":{"enable_image":false,"image":"shopify:\/\/shop_images\/Icon_4.jpg","image_mask":"none","image_width":200,"title":"Returns & Refunds","text":"","style_link":false,"chat_btn":false,"button_label":"GO TO RETAIL INQUIRY FORM","button_link":"shopify:\/\/pages\/retail-inquiries"}}},"block_order":["1652699006e9e7c9bd-0","1652699006e9e7c9bd-1"],"custom_css":[".btn {min-width: 100%; background: #000; color: #fff;}",".grid__item {padding-left: 0; max-width: 362px;}",".grid {margin: 0; display: flex; align-items: center; gap: 40px; flex-direction: column;}","h3 {font-family: \"Montserrat\" !important; font-weight: 600; text-transform: capitalize;}","@media (min-width: 769px) {h3 {font-size: 25px; }}","@media (max-width: 767px) {.custom-collection-list:nth-child(2n) > div {padding: 0 30px; } .grid__item {width: 100%; margin-bottom: 0px !important; } .grid {gap: 12px; }}"],"settings":{"title":"","btntext":"","btnurl":"","text":"","align_text":"center","divider":false,"mobile_link":""}},"rich_text_4xMBnc":{"type":"rich-text","blocks":{"text_m3jyBq":{"type":"text","settings":{"enlarge_text":false,"text":"<h3>Need quick help?<\/h3>"}},"text_n4B73F":{"type":"text","settings":{"enlarge_text":false,"text":"<p>Visit our quick links to <a href=\"\/pages\/support-center\" title=\"International  Customers\">FAQs<\/a> that can help you.<\/p>"}}},"block_order":["text_m3jyBq","text_n4B73F"],"custom_css":[".theme-block,h4 {margin: 0;}",".custom-rich-text {margin-bottom: 25px;}","h3 {font-family: \"Montserrat\" !important; text-transform: none; font-weight: 600; margin: 0px 0 10px; font-size: 20px;}","@media (min-width: 769px) {h3 {font-size: 25px; }}","@media (max-width: 767px) {.custom-rich-text > div > div {padding: 0px 10px; margin-bottom: 0; } .custom-rich-text {margin-bottom: 0; } .custom-rich-text div p {font-size: 18px; }}"],"settings":{"desktop_hide":false,"mobile_hide":false,"align_text":"center","narrow_column":false,"divider":false,"padding_b":30}}},"order":["1651070082ce909d70","rich_text_qARr8A","16510701485bc85b9d","165269900644ff2f31","rich_text_4xMBnc"]}